./.gitignore
./.python-version
./PKG-INFO
./README.md
./main.py
./puppeteer.py
./pyproject.toml
./server.json
./uv.lock
android_puppeteer_mcp-1.0.1.dist-info/METADATA
android_puppeteer_mcp-1.0.1.dist-info/WHEEL
android_puppeteer_mcp-1.0.1.dist-info/entry_points.txt
android_puppeteer_mcp-1.0.1.dist-info/RECORD
