Metadata-Version: 2.4
Name: android-puppeteer-mcp
Version: 1.0.1
Summary: MCP server for Android automation with UI interaction, screenshots, and device control
Requires-Python: >=3.10
Requires-Dist: mcp[cli]>=1.14.0
Requires-Dist: pillow>=10.0.0
Requires-Dist: uiautomator2>=3.0.0
